meta1_pricefeed
